{
    "page_settings": {
        "page_title": "Shop",
        "page_description": "One of our best items to choose from",
        "hide_page_title_on_desktop": "_",
        "page_animate_scroll_to_content": "1 == 1",
        "page_quote": "Christina is a natural light photographer, specializing in families and children. Based in Woodridge, IL and serving surrounding areas of Chicago. Also available for travel!",
        "contact_menu_name": "contact",
        "item_display_type": "item_without_btn_with_click"
    }
}